{
  "tabell_id": 851,
  "api_versjon": 1,
  "statuslinje": "N",
  "begrensning": "10",
  "kodetekst": "N",
  "desimal_separator": ".",
  "variabler": [
    "Tidsskrift id",
    "Original tittel",
    "Online ISSN",
    "Print ISSN",
    "Open Access",
    "Spr책k",
    "NPI Fagfelt",
    "Url",
    "Niv책 2020",
    "Etablert 책r",
    "Nedlagt 책r"
  ],
  "sortBy": ["Original tittel"],
  "filter": [
    {
      "variabel": "Original tittel",
      "selection": {
        "filter": "like",
        "values": [
          "%"
        ]
      }
    }
  ]
}
